mayautil/__init__.py
mayautil/node.py
maya_util-0.3.1.dist-info/LICENSE
maya_util-0.3.1.dist-info/WHEEL
maya_util-0.3.1.dist-info/METADATA
maya_util-0.3.1.dist-info/RECORD
